odoo8_addon_l10n_ca_qc_account_fiscal_position_rule-8.0.1.0.0-py2.7-nspkg.pth
odoo_addons/l10n_ca_qc_account_fiscal_position_rule/__openerp__.py
odoo_addons/l10n_ca_qc_account_fiscal_position_rule/__init__.py
odoo_addons/l10n_ca_qc_account_fiscal_position_rule/README.rst
odoo_addons/l10n_ca_qc_account_fiscal_position_rule/data/account_fiscal_position_rule.xml
odoo_addons/l10n_ca_qc_account_fiscal_position_rule/static/description/rules01.png
odoo_addons/l10n_ca_qc_account_fiscal_position_rule/static/description/icon.png
odoo8_addon_l10n_ca_qc_account_fiscal_position_rule-8.0.1.0.0.dist-info/top_level.txt
odoo8_addon_l10n_ca_qc_account_fiscal_position_rule-8.0.1.0.0.dist-info/WHEEL
odoo8_addon_l10n_ca_qc_account_fiscal_position_rule-8.0.1.0.0.dist-info/RECORD
odoo8_addon_l10n_ca_qc_account_fiscal_position_rule-8.0.1.0.0.dist-info/metadata.json
odoo8_addon_l10n_ca_qc_account_fiscal_position_rule-8.0.1.0.0.dist-info/DESCRIPTION.rst
odoo8_addon_l10n_ca_qc_account_fiscal_position_rule-8.0.1.0.0.dist-info/METADATA
odoo8_addon_l10n_ca_qc_account_fiscal_position_rule-8.0.1.0.0.dist-info/namespace_packages.txt
