Metadata-Version: 2.0
Name: odoo8-addon-l10n-ca-qc-account-fiscal-position-rule
Version: 8.0.1.0.0
Summary: Account Fiscal Position Rules for Quebec, Canada
Home-page: http://www.savoirfairelinux.com
Author: UNKNOWN
Author-email: UNKNOWN
License: AGPL-3
Platform: UNKNOWN
Requires-Dist: odoo (<9.0a,>=8.0a)
Requires-Dist: odoo8-addon-account-fiscal-position-rule-purchase
Requires-Dist: odoo8-addon-account-fiscal-position-rule-sale
Requires-Dist: odoo8-addon-account-fiscal-position-rule-stock
Requires-Dist: odoo8-addon-l10n-ca-toponyms
Classifier: Programming Language :: Python :: 2.7
Classifier: Framework :: Odoo
Classifier: License :: OSI Approved :: GNU Affero General Public License v3
